appmode/__init__.py
appmode/appmode.html
appmode/appmode_bottom.css
appmode/appmode_top.css
appmode/server_extension.py
appmode/static/gears.svg
appmode/static/main.js
appmode_aiidalab-0.5.0.1.data/data/share/jupyter/nbextensions/appmode/gears.svg
appmode_aiidalab-0.5.0.1.data/data/share/jupyter/nbextensions/appmode/main.js
appmode_aiidalab-0.5.0.1.dist-info/LICENSE.txt
appmode_aiidalab-0.5.0.1.dist-info/METADATA
appmode_aiidalab-0.5.0.1.dist-info/WHEEL
appmode_aiidalab-0.5.0.1.dist-info/top_level.txt
appmode_aiidalab-0.5.0.1.dist-info/RECORD
