Metadata-Version: 2.1
Name: appmode-aiidalab
Version: 0.5.0.1
Summary: A Jupyter extensions that turns notebooks into web applications, with modifications for AiiDA lab.
Home-page: http://github.com/materials-org/appmode-aiidalab
Author: Ole Schuett
Author-email: ole.schuett@cp2k.org
License: MIT
Platform: UNKNOWN
Classifier: Programming Language :: Python :: 2
Classifier: Programming Language :: Python :: 2.7
Classifier: Programming Language :: Python :: 3
Classifier: Programming Language :: Python :: 3.5
Classifier: License :: OSI Approved :: MIT License
Classifier: Operating System :: OS Independent
Requires-Dist: notebook (>=5)
